{
  "workflow_id": "sample_historical_analysis",
  "graphs": [{"id": "GRAPH_TECHNOLOGICAL_EVOLUTION", "figure_width": 6, "figure_height": 4, "title": "古代ローマのWi-Fi技術と現代技術の進化比較", "xlabel": "技術発展の時間軸", "ylabel": "技術的複雑性", "grid": true, "legend": true, "charts": [{"chart_type": "line", "lines": [{"x": [0, 50, 100, 150, 200], "y": [1, 3, 5, 7, 10], "label": "古代ローマ通信技術", "color": "blue", "linestyle": "-", "marker": "o"}, {"x": [0, 50, 100, 150, 200], "y": [1, 2, 4, 8, 16], "label": "現代Wi-Fi技術", "color": "red", "linestyle": "--", "marker": "x"}]}]}, {"id": "GRAPH_COMMUNICATION_NETWORK", "figure_width": 6, "figure_height": 4, "title": "アエリウス・ネットワークの通信範囲", "xlabel": "地理的距離 (km)", "ylabel": "通信効率", "grid": true, "legend": true, "charts": [{"chart_type": "line", "lines": [{"x": [0, 50, 100, 200, 300, 400], "y": [1.0, 0.9, 0.7, 0.5, 0.3, 0.2], "label": "通信効率", "color": "blue", "linestyle": "-", "marker": "o"}]}]}, {"id": "GRAPH_IMPERIAL_EXPANSION", "figure_width": 6, "figure_height": 4, "title": "通信技術が帝国拡大に与えた影響", "xlabel": "年代", "ylabel": "帝国の影響力", "grid": true, "legend": true, "charts": [{"chart_type": "line", "lines": [{"x": [0, 50, 100, 150, 200], "y": [1, 3, 5, 7, 9], "label": "通信技術なし", "color": "red", "linestyle": "--", "marker": "o"}, {"x": [0, 50, 100, 150, 200], "y": [1, 4, 7, 10, 15], "label": "通信技術あり", "color": "blue", "linestyle": "-", "marker": "x"}]}]}, {"id": "GRAPH_TECHNOLOGICAL_LINEAGE", "figure_width": 6, "figure_height": 4, "title": "通信技術の歴史的系譜", "xlabel": "技術発展の時間軸", "ylabel": "技術的複雑性", "grid": true, "legend": true, "charts": [{"chart_type": "line", "lines": [{"x": [0, 100, 200, 300, 400, 500], "y": [1, 2, 3, 5, 8, 13], "label": "ローマ帝国通信技術", "color": "blue", "linestyle": "-", "marker": "o"}, {"x": [0, 100, 200, 300, 400, 500], "y": [1, 1.5, 2.5, 4, 7, 12], "label": "現代通信技術", "color": "red", "linestyle": "--", "marker": "x"}]}]}, {"id": "GRAPH_INFORMATION_DISPARITY", "figure_width": 6, "figure_height": 4, "title": "情報格差の歴史的変遷", "xlabel": "時代", "ylabel": "情報アクセス平等性", "grid": true, "legend": true, "charts": [{"chart_type": "line", "lines": [{"x": [0, 100, 200, 300, 400, 500], "y": [0.1, 0.3, 0.5, 0.7, 0.8, 0.9], "label": "ローマ帝国の情報民主化", "color": "blue", "linestyle": "-", "marker": "o"}, {"x": [0, 100, 200, 300, 400, 500], "y": [0.1, 0.2, 0.4, 0.6, 0.7, 0.8], "label": "現代の情報アクセス", "color": "red", "linestyle": "--", "marker": "x"}]}]}, {"id": "GRAPH_TECHNOLOGICAL_LESSONS", "figure_width": 6, "figure_height": 4, "title": "技術革新の教訓：歴史的視点", "xlabel": "技術的理解の深さ", "ylabel": "社会的影響力", "grid": true, "legend": true, "charts": [{"chart_type": "scatter", "x": [0.2, 0.4, 0.6, 0.8, 1.0], "y": [0.3, 0.5, 0.7, 0.8, 0.9], "colors": [0.2, 0.4, 0.6, 0.8, 1.0], "sizes": [50, 70, 90, 110, 130], "alpha": 0.7, "cmap": "viridis"}]}, {"id": "GRAPH_MODERN_APPLICATIONS", "figure_width": 6, "figure_height": 4, "title": "古代技術の現代的応用", "xlabel": "技術的領域", "ylabel": "応用可能性", "grid": true, "legend": true, "charts": [{"chart_type": "bar", "categories": ["サイバーセキュリティ", "災害通信", "社会的包摂", "分散型ネットワーク"], "values": [0.8, 0.7, 0.6, 0.9], "colors": ["blue", "green", "red", "purple"]}]}]
}
